aprilbox/__init__.py
aprilbox/types.py
aprilbox/ai/__init__.py
aprilbox/ai/dl/__init__.py
aprilbox/ai/dl/activation/__init__.py
aprilbox/ai/dl/activation/acon.py
aprilbox/ai/dl/activation/smu.py
aprilbox/ai/dl/backbone/__init__.py
aprilbox/ai/dl/backbone/lstm.py
aprilbox/ai/dl/backbone/resnet.py
aprilbox/ai/dl/backbone/unet.py
aprilbox/ai/dl/backbone/vit.py
aprilbox/ai/dl/benchmark/__init__.py
aprilbox/ai/dl/benchmark/scinet.py
aprilbox/ai/dl/benchmark/simvp.py
aprilbox/ai/dl/block/__init__.py
aprilbox/ai/dl/block/cca.py
aprilbox/ai/dl/block/conv.py
aprilbox/ai/dl/block/inception.py
aprilbox/ai/dl/block/memory.py
aprilbox/ai/dl/block/attention/__init__.py
aprilbox/ai/dl/block/attention/lka.py
aprilbox/ai/dl/block/attention/psa.py
aprilbox/ai/dl/block/attention/simple.py
aprilbox/ai/dl/block/attention/split.py
aprilbox/ai/dl/loss/__init__.py
aprilbox/ai/dl/loss/dice.py
aprilbox/ai/dl/loss/focal.py
aprilbox/ai/dl/loss/loss.py
aprilbox/ai/dl/loss/rmse.py
aprilbox/ai/dl/loss/seesaw.py
aprilbox/ai/dl/loss/ssim.py
aprilbox/ai/dl/loss/ts.py
aprilbox/ai/ml/__init__.py
aprilbox/ai/tools/__init__.py
aprilbox/ai/tools/base.py
aprilbox/ai/tools/config.py
aprilbox/ai/tools/weight.py
aprilbox/data/__init__.py
aprilbox/data/met/__init__.py
aprilbox/data/met/constant.py
aprilbox/data/met/loader.py
aprilbox/data/preprocess/__init__.py
aprilbox/eval/__init__.py
aprilbox/utils/__init__.py
aprilbox/utils/interpolate.py
aprilbox/utils/path.py
aprilbox/utils/pool.py
aprilbox/utils/met/__init__.py
aprilbox/utils/met/distance.py
aprilbox/utils/met/factor.py
aprilbox/vis/__init__.py
aprilbox/vis/base.py
aprilbox/vis/precipitation.py
aprilbox-1.0.0b5.dist-info/LICENSE
aprilbox-1.0.0b5.dist-info/METADATA
aprilbox-1.0.0b5.dist-info/WHEEL
aprilbox-1.0.0b5.dist-info/top_level.txt
aprilbox-1.0.0b5.dist-info/RECORD
