Metadata-Version: 2.1
Name: aprilbox
Version: 1.0.0b5
Summary: UNKNOWN
Home-page: UNKNOWN
Author: Fang Linwanghao
Author-email: fanglwh@outlook.com
License: BSD-3-Clause
Platform: UNKNOWN
License-File: LICENSE
Requires-Dist: matplotlib (~=3.5.0)
Requires-Dist: netCDF4 (~=1.5.7)
Requires-Dist: numpy (~=1.19.5)
Requires-Dist: opencv-python (~=4.5.5.62)
Requires-Dist: pandas (~=1.3.5)
Requires-Dist: pygrib (~=2.1.4)
Requires-Dist: scikit-image (~=0.18.3)
Requires-Dist: scipy (~=1.5.3)
Requires-Dist: setuptools (~=58.0.4)
Requires-Dist: torch (~=1.10.0)
